azlet/__init__.py
azlet/__main__.py
azlet/azertbot.py
azlet/dns_providers/__init__.py
azlet/dns_providers/azuredns.py
azlet-0.9.1.dist-info/LICENSE
azlet-0.9.1.dist-info/METADATA
azlet-0.9.1.dist-info/WHEEL
azlet-0.9.1.dist-info/top_level.txt
azlet-0.9.1.dist-info/RECORD
