Metadata-Version: 2.1
Name: azlet
Version: 0.9.1
Summary: Python package to create/renew certificates using azure DNS and azure KeyVault
Home-page: https://github.com/claasd/azlet
Author: Claas Diederichs
Author-email: 
License: MIT
Platform: UNKNOWN
Classifier: Programming Language :: Python :: 3.6
Classifier: Programming Language :: Python :: 3.7
Classifier: Programming Language :: Python :: 3.8
Classifier: Programming Language :: Python :: 3.9
Classifier: License :: OSI Approved :: MIT License
Classifier: Operating System :: OS Independent
Requires-Python: >=3.6
License-File: LICENSE
Requires-Dist: pem
Requires-Dist: sewer (==0.8.4)
Requires-Dist: azure-keyvault-certificates (~=4.2)
Requires-Dist: azure-keyvault-secrets (~=4.2)
Requires-Dist: azure-identity (~=1.5)
Requires-Dist: azure-mgmt-dns (~=8.0)
Requires-Dist: pyopenssl
